{"1": {
 "calculator": "vasp",
 "calculator_parameters": {"amix": 0.1, "amix_mag": 0.1, "bmix": 1e-05, "bmix_mag": 1e-05, "encut": 600, "sigma": 0.05, "ediff": 1e-06, "ediffg": -0.02, "algo": "normal", "gga": "PE", "prec": "Normal", "ibrion": -1, "icharg": 11, "isif": 3, "ismear": 0, "ispin": 2, "istart": 1, "isym": 0, "kpar": 10, "ldauprint": 2, "ldautype": 2, "lmaxmix": 4, "lorbit": 11, "nbands": 54, "nelm": 250, "npar": 6, "nsw": 0, "nedos": 3000, "inimix": 0, "laechg": true, "lasph": true, "ldau": true, "lvtot": false, "lreal": false, "ldau_luj": {"Ti": {"L": 2, "U": 3.0, "J": 0.0}, "V": {"L": 2, "U": 3.25, "J": 0.0}, "Cr": {"L": 2, "U": 3.5, "J": 0.0}, "Mn": {"L": 2, "U": 3.75, "J": 0.0}, "Fe": {"L": 2, "U": 4.3, "J": 0.0}, "Co": {"L": 2, "U": 3.32, "J": 0.0}, "Ni": {"L": 2, "U": 6.45, "J": 0.0}, "Cu": {"L": 2, "U": 3.0, "J": 0.0}, "Mo": {"L": 2, "U": 4.38, "J": 0.0}, "W": {"L": 2, "U": 3.0, "J": 0.0}, "Ce": {"L": 3, "U": 4.5, "J": 0.0}, "O": {"L": -1, "U": 0.0, "J": 0.0}, "C": {"L": -1, "U": 0.0, "J": 0.0}, "Au": {"L": -1, "U": 0.0, "J": 0.0}, "Ir": {"L": -1, "U": 0.0, "J": 0.0}, "H": {"L": -1, "U": 0.0, "J": 0.0}}, "xc": "PBE", "pp": "PBE", "setups": {"base": "minimal"}, "txt": "-", "kpts": [10, 10, 16], "gamma": true, "reciprocal": false, "ignore_constraints": false},
 "cell": [[2.8186395845, 2.8186395844999996, -3.986158327841566], [2.8186395844999996, 2.8186395845, 3.986158327841565], [2.2515729701084206, -2.2515729701084197, 1.3786908154449881e-16]],
 "ctime": 21.49424368488679,
 "dipole": [[0.0, 0.0, 0.0]],
 "energy": -18.3089007,
 "forces": [[-6.5e-05, 5.8e-05, 0.0], [8.7e-05, -6.3e-05, 2e-06], [-0.001057, -0.001034, -0.0], [0.001022, 0.001071, -1e-06], [7e-06, -1.6e-05, -0.001467], [7e-06, -1.5e-05, 0.001466]],
 "initial_charges": [1.37, 1.37, -0.69, -0.68, -0.68, -0.68],
 "initial_magmoms": [0.0, 0.0, 0.0, 0.0, 0.0, 0.0],
 "mtime": 21.49424368488679,
 "numbers": [80, 80, 8, 8, 8, 8],
 "pbc": [true, true, true],
 "positions": [[0.0, 0.0, 0.0], [3.9444247063270996, 1.6928552936729093, 1.9481749629029732e-17], [1.8953100000000038, 1.8953100000000043, -1.0599033868043256e-16], [3.7419700000000033, 3.741970000000004, -2.1495963069979132e-16], [3.944424706327099, 1.6928552936729089, 2.680373106901357], [3.9444247063270987, 1.6928552936729084, -2.6803731069013566]],
 "stress": [-0.0004553118492240578, -0.0004552931246966801, -0.0008864128845488145, -0.0, 1.8724527377649774e-08, -0.0004390027858781248],
 "unique_id": "7f29762f6e423195a86452a8e52ba6ef",
 "user": "bcomer3"},
"ids": [1],
"nextid": 2}
